review_bot_automator/__init__.py
review_bot_automator/py.typed
review_bot_automator/analysis/__init__.py
review_bot_automator/analysis/conflict_detector.py
review_bot_automator/benchmarks/__init__.py
review_bot_automator/benchmarks/utils.py
review_bot_automator/cli/__init__.py
review_bot_automator/cli/config_loader.py
review_bot_automator/cli/llm_error_handler.py
review_bot_automator/cli/main.py
review_bot_automator/config/__init__.py
review_bot_automator/config/exceptions.py
review_bot_automator/config/presets.py
review_bot_automator/config/runtime_config.py
review_bot_automator/core/__init__.py
review_bot_automator/core/models.py
review_bot_automator/core/resolver.py
review_bot_automator/core/rollback.py
review_bot_automator/handlers/__init__.py
review_bot_automator/handlers/base.py
review_bot_automator/handlers/json_handler.py
review_bot_automator/handlers/toml_handler.py
review_bot_automator/handlers/yaml_handler.py
review_bot_automator/integrations/__init__.py
review_bot_automator/integrations/github.py
review_bot_automator/llm/__init__.py
review_bot_automator/llm/base.py
review_bot_automator/llm/config.py
review_bot_automator/llm/constants.py
review_bot_automator/llm/cost_tracker.py
review_bot_automator/llm/error_handlers.py
review_bot_automator/llm/exceptions.py
review_bot_automator/llm/factory.py
review_bot_automator/llm/metrics.py
review_bot_automator/llm/metrics_aggregator.py
review_bot_automator/llm/parallel_parser.py
review_bot_automator/llm/parser.py
review_bot_automator/llm/presets.py
review_bot_automator/llm/cache/__init__.py
review_bot_automator/llm/cache/prompt_cache.py
review_bot_automator/llm/prompts/__init__.py
review_bot_automator/llm/prompts/base_prompt.py
review_bot_automator/llm/prompts/examples.py
review_bot_automator/llm/providers/__init__.py
review_bot_automator/llm/providers/anthropic_api.py
review_bot_automator/llm/providers/base.py
review_bot_automator/llm/providers/caching_provider.py
review_bot_automator/llm/providers/claude_cli.py
review_bot_automator-2.0.2.dist-info/METADATA
review_bot_automator-2.0.2.dist-info/WHEEL
review_bot_automator-2.0.2.dist-info/entry_points.txt
review_bot_automator-2.0.2.dist-info/licenses/LICENSE
review_bot_automator-2.0.2.dist-info/RECORD
