Metadata-Version: 2.4
Name: review-bot-automator
Version: 2.0.2
Summary: Universal AI-powered automation for GitHub code review bots with intelligent conflict resolution
Project-URL: Homepage, https://github.com/VirtualAgentics/review-bot-automator
Project-URL: Documentation, https://github.com/VirtualAgentics/review-bot-automator/blob/main/docs/
Project-URL: Repository, https://github.com/VirtualAgentics/review-bot-automator
Project-URL: Issues, https://github.com/VirtualAgentics/review-bot-automator/issues
Author-email: VirtualAgentics <bdc@virtualagentics.ai>
License: MIT
License-File: LICENSE
Keywords: ai,automation,code-review,code-review-bot,coderabbit,conflict-resolution,github,github-copilot,llm,pr-automation,suggestion-applier
Classifier: Development Status :: 3 - Alpha
Classifier: Intended Audience :: Developers
Classifier: License :: OSI Approved :: MIT License
Classifier: Operating System :: POSIX :: Linux
Classifier: Programming Language :: Python :: 3
Classifier: Programming Language :: Python :: 3.11
Classifier: Programming Language :: Python :: 3.12
Classifier: Topic :: Software Development :: Quality Assurance
Classifier: Topic :: Software Development :: Version Control :: Git
Requires-Python: >=3.11
Requires-Dist: anthropic==0.75.0
Requires-Dist: click==8.3.1
Requires-Dist: openai==2.8.1
Requires-Dist: pydantic==2.12.5
Requires-Dist: requests==2.32.5
Requires-Dist: rich==14.2.0
Requires-Dist: ruamel-yaml==0.18.16
Requires-Dist: tenacity==9.1.2
Requires-Dist: tiktoken==0.12.0
Requires-Dist: tomli-w==1.2.0
Provides-Extra: dev
Requires-Dist: bandit[toml]==1.9.2; extra == 'dev'
Requires-Dist: black==25.11.0; extra == 'dev'
Requires-Dist: build==1.3.0; extra == 'dev'
Requires-Dist: hypothesis==6.148.6; extra == 'dev'
Requires-Dist: mypy==1.19.0; extra == 'dev'
Requires-Dist: myst-parser==4.0.1; extra == 'dev'
Requires-Dist: pip-audit==2.9.0; extra == 'dev'
Requires-Dist: pre-commit==4.5.0; extra == 'dev'
Requires-Dist: pytest-cov==7.0.0; extra == 'dev'
Requires-Dist: pytest==9.0.1; extra == 'dev'
Requires-Dist: ruff==0.14.8; extra == 'dev'
Requires-Dist: sphinx-autodoc-typehints==3.5.2; extra == 'dev'
Requires-Dist: sphinx-rtd-theme==3.0.2; extra == 'dev'
Requires-Dist: sphinx==8.2.3; extra == 'dev'
Requires-Dist: twine==6.2.0; extra == 'dev'
Requires-Dist: types-pyyaml==6.0.12.20250915; extra == 'dev'
Requires-Dist: types-requests==2.32.4.20250913; extra == 'dev'
Provides-Extra: ml
Requires-Dist: numpy==2.3.5; extra == 'ml'
Requires-Dist: scikit-learn==1.7.2; extra == 'ml'
